goes_ortho/Downloader.py
goes_ortho/__init__.py
goes_ortho/checkData.py
goes_ortho/clip.py
goes_ortho/geometry.py
goes_ortho/get_data.py
goes_ortho/io.py
goes_ortho/orthorectify.py
goes_ortho/rad.py
goes_ortho/timeseries.py
goes_ortho/utils.py
goes_ortho/version.py
goes_ortho-0.2.1.5.dist-info/METADATA
goes_ortho-0.2.1.5.dist-info/WHEEL
goes_ortho-0.2.1.5.dist-info/licenses/LICENSE
goes_ortho-0.2.1.5.dist-info/RECORD
