Metadata-Version: 2.3
Name: goes_ortho
Version: 0.2.1.5
Summary: A python package for downloading GOES-R ABI imagery, orthorectifying with a DEM, and creating timeseries
Project-URL: Homepage, https://spestana.github.io/goes_ortho
Project-URL: Repository, https://github.com/spestana/goes_ortho
Project-URL: Issues, https://github.com/spestana/goes_ortho/issues
Author-email: Steven Pestana <spestana@uw.edu>
License:                     GNU GENERAL PUBLIC LICENSE
License-File: LICENSE
Requires-Python: >=3.8
Requires-Dist: aiohttp
Requires-Dist: awscli
Requires-Dist: black
Requires-Dist: boto3
Requires-Dist: cfgrib
Requires-Dist: cftime
Requires-Dist: dask
Requires-Dist: distributed
Requires-Dist: flake8
Requires-Dist: folium
Requires-Dist: fsspec
Requires-Dist: gdal<=3.8
Requires-Dist: gdown
Requires-Dist: geogif
Requires-Dist: geopandas
Requires-Dist: h5netcdf
Requires-Dist: hvplot
Requires-Dist: ipykernel
Requires-Dist: matplotlib
Requires-Dist: netcdf4
Requires-Dist: numpy
Requires-Dist: pandas
Requires-Dist: pathlib
Requires-Dist: pooch
Requires-Dist: pydap
Requires-Dist: pyproj
Requires-Dist: rasterio
Requires-Dist: requests
Requires-Dist: rioxarray
Requires-Dist: s3fs
Requires-Dist: scikit-learn
Requires-Dist: scipy
Requires-Dist: tqdm
Requires-Dist: xarray
Requires-Dist: zarr
Provides-Extra: dev
Requires-Dist: nox; extra == 'dev'
Requires-Dist: pre-commit>=2.17.0; extra == 'dev'
Requires-Dist: pytest>=6.2.5; extra == 'dev'
Provides-Extra: doc
Requires-Dist: furo; extra == 'doc'
Requires-Dist: ghp-import; extra == 'doc'
Requires-Dist: ipykernel; extra == 'doc'
Requires-Dist: myst-parser; extra == 'doc'
Requires-Dist: nbsphinx; extra == 'doc'
Requires-Dist: pandoc; extra == 'doc'
Requires-Dist: sphinx; extra == 'doc'
